{
  "Contents": {
    "29347a66-97a2-414c-81dd-3daf0a9d16bc": {
      "type": "TILE_WALL",
      "transform": "0,-5,0,0.2,0.2"
    },
    "1bb4f515-c021-4c10-9bc5-22bade073771": {
      "type": "BLACKBOX",
      "transform": "-21.95,-0.24,0,2,2"
    },
    "camera": {
      "size": "7.89",
      "z": "-10",
      "type": "CAMERA",
      "transform": "0,0,0,1,1"
    },
    "8f728316-8189-4558-91ff-a919c9f76712": {
      "type": "BLACKBOX",
      "transform": "0.41,10.09,0,3,1"
    },
    "7399d688-57b4-4b20-a8aa-a4d6fe49cc11": {
      "type": "FLOOR",
      "transform": "-1.676652,-1.122928,0,0.5,0.5"
    },
    "0157b7fb-69f7-4bd0-a513-ba5e29bb3d14": {
      "type": "TILE_WALL",
      "transform": "-12,0,0,0.2,0.2"
    },
    "b80e302c-2061-4dbd-90f1-b9302d82d01c": {
      "type": "TILE_WALL",
      "transform": "0,5,0,0.2,0.2"
    },
    "2": {
      "type": "CAT_WHISTLE",
      "transform": "5,-3,0,1.2,1.2"
    },
    "player": {
      "Inventory": "",
      "type": "PLAYER",
      "transform": "-2,1,0,1.4,1.4"
    },
    "19f539b2-c548-485a-8380-9290b01081dc": {
      "type": "BLACKBOX",
      "transform": "0.47,-10.1,0,3,1"
    },
    "716a3d6e-3284-4f91-be11-db4e5f7bf34b": {
      "type": "CAT",
      "transform": "-10,-2.05,0,1.5,1.5"
    },
    "12311b49-14dd-4f7c-a8de-73b96df5216a": {
      "Level": "level1",
      "type": "EXIT",
      "transform": "11.75,0.04,0,1,2.687501"
    },
    "9f9fd7fc-4441-443a-95bc-2f45cd0d342a": {
      "type": "BLACKBOX",
      "transform": "22.01,-0.12,0,2,2"
    },
    "30dd18ae-c85e-4165-98f1-5fc0c9d8cd79": {
      "type": "TILE_WALL",
      "transform": "12,0,0,0.2,0.2"
    }
  },
  "Name": "level0_Redo"
}