{
  "Contents": {
    "3eea93b6-5d66-4e4f-b544-1088ad022f9d": {
      "type": "KEY",
      "transform": "3,5.5,0,1,1"
    },
    "2f0afad2-8d47-4ac5-b57b-3eb711ad9ac1": {
      "type": "WALL",
      "transform": "-4.6,-2.8,0,0.1,1"
    },
    "08d005eb-9abd-40fe-b10f-403fb3d4c744": {
      "type": "WALL",
      "transform": "-7,0,0,0.1,5"
    },
    "a69d7a30-6e91-4006-94b9-1f55364b7deb": {
      "type": "DOOR",
      "transform": "-5.8,-4,90,1,1"
    },
    "996e7c88-713e-449e-8437-3f3478b2cc4d": {
      "type": "WALL",
      "transform": "-1.1,6.5,90,0.1,4.6"
    },
    "d69f3750-5ffd-4213-910f-517f42e285ba": {
      "type": "WALL",
      "transform": "-2.1,-2.8,0,0.1,1"
    },
    "c9f6e8dc-bd83-4e9f-adc8-b6e24fe964f0": {
      "type": "WALL",
      "transform": "-3.35,-4.05,90,0.1,1"
    },
    "b847c689-7bba-4be6-b62c-37eea58c0de2": {
      "type": "MIRROR",
      "transform": "6,-5.4,320,0.1,1"
    },
    "4f99875c-b305-4b89-a21b-649fbe1e3ba9": {
      "type": "WINDOW",
      "transform": "7,0,0,0.1,5"
    },
    "camera": {
      "size": "7.89",
      "z": "-10",
      "type": "CAMERA",
      "transform": "0,0,0,1,1"
    },
    "9b21fc16-f4e6-46af-afd1-40ae38b7c66d": {
      "type": "WALL",
      "transform": "-3.35,-1.55,90,0.1,1"
    },
    "player": {
      "type": "PLAYER",
      "transform": "-3.11,-2.85,0,1,1"
    },
    "45cf3072-b279-4462-8248-6a592395bec3": {
      "type": "BARS",
      "transform": "-4.6,-5.2,0,0.1,1"
    },
    "446d6095-c76f-41fa-9862-659fb2b2d530": {
      "type": "WINDOW",
      "transform": "1.1,-6.5,90,0.1,4.6"
    },
    "7a38be1c-2302-4411-9c7d-a3b058606907": {
      "type": "CAT",
      "transform": "-5.7,-4.8,0,1,1"
    }
  },
  "Name": "level2"
}